cloudevents_pydantic/__init__.py
cloudevents_pydantic/py.typed
cloudevents_pydantic/version.py
cloudevents_pydantic/bindings/__init__.py
cloudevents_pydantic/bindings/http.py
cloudevents_pydantic/events/__init__.py
cloudevents_pydantic/events/_event.py
cloudevents_pydantic/events/fields/__init__.py
cloudevents_pydantic/events/fields/metadata/__init__.py
cloudevents_pydantic/events/fields/metadata/_fields.py
cloudevents_pydantic/events/fields/types/__init__.py
cloudevents_pydantic/events/fields/types/_canonic_types.py
cloudevents_pydantic/formats/__init__.py
cloudevents_pydantic/formats/canonical.py
cloudevents_pydantic/formats/json.py
cloudevents_pydantic-0.2.0.dist-info/METADATA
cloudevents_pydantic-0.2.0.dist-info/WHEEL
cloudevents_pydantic-0.2.0.dist-info/licenses/LICENSE
cloudevents_pydantic-0.2.0.dist-info/RECORD
