Metadata-Version: 2.4
Name: cloudevents-pydantic
Version: 0.2.0
Summary: An implementation of the CloudEvents spec using Pydantic V2
Project-URL: Homepage, https://febus982.github.io/cloudevents-pydantic
Project-URL: Repository, https://github.com/febus982/cloudevents-pydantic
Author-email: Federico Busetti <729029+febus982@users.noreply.github.com>
License-Expression: MIT
License-File: LICENSE
Classifier: Development Status :: 4 - Beta
Classifier: Framework :: Pydantic
Classifier: Framework :: Pydantic :: 2
Classifier: Intended Audience :: Developers
Classifier: License :: OSI Approved :: MIT License
Classifier: Natural Language :: English
Classifier: Operating System :: OS Independent
Classifier: Programming Language :: Python
Classifier: Programming Language :: Python :: 3
Classifier: Programming Language :: Python :: 3 :: Only
Classifier: Programming Language :: Python :: 3.9
Classifier: Programming Language :: Python :: 3.10
Classifier: Programming Language :: Python :: 3.11
Classifier: Programming Language :: Python :: 3.12
Classifier: Programming Language :: Python :: 3.13
Classifier: Programming Language :: Python :: 3.14
Classifier: Typing :: Typed
Requires-Python: <3.15,>=3.9
Requires-Dist: cloudevents<2,>=1.11.0
Requires-Dist: pydantic<3,>=2.9.1
Requires-Dist: python-ulid<4,>=3.0.0
